meitei_senter/__init__.py
meitei_senter/cli.py
meitei_senter/meitei_senter.json
meitei_senter/meitei_senter.pth
meitei_senter/meitei_tokenizer.model
meitei_senter/meitei_tokenizer.vocab
meitei_senter/model.py
meitei_senter/server.py
meitei_senter/tokenizer.py
meitei_senter-1.1.2.dist-info/licenses/LICENSE
meitei_senter-1.1.2.dist-info/METADATA
meitei_senter-1.1.2.dist-info/WHEEL
meitei_senter-1.1.2.dist-info/entry_points.txt
meitei_senter-1.1.2.dist-info/top_level.txt
meitei_senter-1.1.2.dist-info/RECORD
