Metadata-Version: 2.4
Name: meitei-senter
Version: 1.1.2
Summary: A lightweight sentence boundary detector for Meitei Mayek (Manipuri) text
Author-email: Okram Jimmy <okramjimmy@gmail.com>
License: MIT
Project-URL: Homepage, https://github.com/Okramjimmy/mni_tokenizer
Project-URL: Documentation, https://github.com/Okramjimmy/mni_tokenizer#readme
Project-URL: Repository, https://github.com/Okramjimmy/mni_tokenizer.git
Project-URL: Issues, https://github.com/Okramjimmy/mni_tokenizer/issues
Keywords: meitei,manipuri,nlp,tokenizer,sentence-splitter,meitei-mayek,sentencepiece,spacy,pytorch
Classifier: Development Status :: 4 - Beta
Classifier: Intended Audience :: Developers
Classifier: Intended Audience :: Science/Research
Classifier: License :: OSI Approved :: MIT License
Classifier: Operating System :: OS Independent
Classifier: Programming Language :: Python :: 3
Classifier: Programming Language :: Python :: 3.9
Classifier: Programming Language :: Python :: 3.10
Classifier: Programming Language :: Python :: 3.11
Classifier: Programming Language :: Python :: 3.12
Classifier: Programming Language :: Python :: 3.13
Classifier: Topic :: Scientific/Engineering :: Artificial Intelligence
Classifier: Topic :: Text Processing :: Linguistic
Requires-Python: >=3.9
License-File: LICENSE
Requires-Dist: sentencepiece>=0.1.99
Requires-Dist: torch>=2.0.0
Requires-Dist: fastapi>=0.100.0
Requires-Dist: uvicorn>=0.20.0
Provides-Extra: spacy
Requires-Dist: spacy>=3.5.0; extra == "spacy"
Provides-Extra: dev
Requires-Dist: pytest; extra == "dev"
Requires-Dist: build; extra == "dev"
Requires-Dist: twine; extra == "dev"
Provides-Extra: all
Requires-Dist: meitei-senter[dev,spacy]; extra == "all"
Dynamic: license-file
